pollination/five_phase/__init__.py
pollination/five_phase/entry.py
pollination/five_phase/direct_sunlight/__init__.py
pollination/five_phase/direct_sunlight/_raytracing.py
pollination/five_phase/direct_sunlight/entry.py
pollination/five_phase/three_phase/__init__.py
pollination/five_phase/three_phase/_daylight_matrix.py
pollination/five_phase/three_phase/_multiply_matrix.py
pollination/five_phase/three_phase/_view_matrix.py
pollination/five_phase/three_phase/calculation.py
pollination/five_phase/three_phase/preparation.py
pollination/five_phase/two_phase/__init__.py
pollination/five_phase/two_phase/_raytracing.py
pollination/five_phase/two_phase/entry.py
pollination_five_phase-0.1.0.dist-info/LICENSE
pollination_five_phase-0.1.0.dist-info/METADATA
pollination_five_phase-0.1.0.dist-info/WHEEL
pollination_five_phase-0.1.0.dist-info/top_level.txt
pollination_five_phase-0.1.0.dist-info/RECORD
